itk/BSplineGradientPython.py
itk/_BSplineGradientPython.pyd
itk/__init_bsplinegradient__.py
itk/itkBSplineGradientImageFilterPython.py
itk/Configuration/BSplineGradientConfig.py
itk/Configuration/BSplineGradient_snake_case.py
itk_bsplinegradient.libs/.load-order-itk_bsplinegradient-0.3.0
itk_bsplinegradient.libs/msvcp140.dll
itk_bsplinegradient.libs/tbb12.dll
itk_bsplinegradient-0.3.0.dist-info/DELVEWHEEL
itk_bsplinegradient-0.3.0.dist-info/LICENSE
itk_bsplinegradient-0.3.0.dist-info/METADATA
itk_bsplinegradient-0.3.0.dist-info/WHEEL
itk_bsplinegradient-0.3.0.dist-info/top_level.txt
itk_bsplinegradient-0.3.0.dist-info/RECORD
