Metadata-Version: 2.1
Name: itk-bsplinegradient
Version: 0.3.0
Summary: Approximate an image's gradient from a B-spline fit to its intensity.
Home-page: https://github.com/InsightSoftwareConsortium/ITKBSplineGradient
Download-URL: https://github.com/InsightSoftwareConsortium/ITKBSplineGradient
Author: Matthew McCormick
Author-email: matt.mccormick@kitware.com
License: Apache
Keywords: ITK InsightToolkit Image-Gradient B-spline
Classifier: License :: OSI Approved :: Apache Software License
Classifier: Programming Language :: Python
Classifier: Programming Language :: C++
Classifier: Development Status :: 4 - Beta
Classifier: Intended Audience :: Developers
Classifier: Intended Audience :: Education
Classifier: Intended Audience :: Healthcare Industry
Classifier: Intended Audience :: Science/Research
Classifier: Topic :: Scientific/Engineering
Classifier: Topic :: Scientific/Engineering :: Medical Science Apps.
Classifier: Topic :: Scientific/Engineering :: Information Analysis
Classifier: Topic :: Software Development :: Libraries
Classifier: Operating System :: Android
Classifier: Operating System :: Microsoft :: Windows
Classifier: Operating System :: POSIX
Classifier: Operating System :: Unix
Classifier: Operating System :: MacOS
License-File: LICENSE
Requires-Dist: itk (>=v5.3rc04.post4)
Requires-Dist: itk-meshtopolydata (>=v0.9.2)
